johndoe/__init__.py
johndoe/findinfo.py
johndoe-0.0.1.dist-info/LICENSE
johndoe-0.0.1.dist-info/METADATA
johndoe-0.0.1.dist-info/WHEEL
johndoe-0.0.1.dist-info/top_level.txt
johndoe-0.0.1.dist-info/RECORD
