Metadata-Version: 2.1
Name: johndoe
Version: 0.0.1
Summary: package for testing package installation process
Home-page: https://gitlab.com/Kingscote
Author: akingscote
Author-email: ashleykingscote@hotmail.co.uk
License: UNKNOWN
Platform: UNKNOWN
Classifier: Programming Language :: Python :: 3
Classifier: License :: OSI Approved :: MIT License
Classifier: Operating System :: OS Independent
Requires-Python: >=3.4
Requires-Dist: psutil
